{"nodes": [{"id": "c_users_muska_onedrive_documents_app_development_aura_fitness_tracker_aurafitness_models_seeddata_swift", "label": "SeedData.swift", "file_type": "code", "source_file": "AuraFitness/Models/SeedData.swift", "source_location": "L1"}, {"id": "foundation", "label": "Foundation", "file_type": "code", "type": "module", "source_file": "AuraFitness/Models/SeedData.swift", "source_location": "L1"}, {"id": "cryptokit", "label": "CryptoKit", "file_type": "code", "type": "module", "source_file": "AuraFitness/Models/SeedData.swift", "source_location": "L2"}, {"id": "c_users_muska_onedrive_documents_app_development_aura_fitness_tracker_aurafitness_models_seeddata_stableid", "label": "StableID", "file_type": "code", "source_file": "AuraFitness/Models/SeedData.swift", "source_location": "L18", "_callable": true}, {"id": "c_users_muska_onedrive_documents_app_development_aura_fitness_tracker_aurafitness_models_seeddata_stableid_program", "label": ".program()", "file_type": "code", "source_file": "AuraFitness/Models/SeedData.swift", "source_location": "L23", "_callable": true}, {"id": "string", "label": "String", "file_type": "code", "source_file": "", "source_location": "", "origin_file": "C:\\Users\\muska\\OneDrive\\Documents\\App Development\\Aura Fitness Tracker\\AuraFitness\\Models\\SeedData.swift"}, {"id": "uuid", "label": "UUID", "file_type": "code", "source_file": "", "source_location": "", "origin_file": "C:\\Users\\muska\\OneDrive\\Documents\\App Development\\Aura Fitness Tracker\\AuraFitness\\Models\\SeedData.swift"}, {"id": "c_users_muska_onedrive_documents_app_development_aura_fitness_tracker_aurafitness_models_seeddata_stableid_workout", "label": ".workout()", "file_type": "code", "source_file": "AuraFitness/Models/SeedData.swift", "source_location": "L24", "_callable": true}, {"id": "c_users_muska_onedrive_documents_app_development_aura_fitness_tracker_aurafitness_models_seeddata_stableid_exercise", "label": ".exercise()", "file_type": "code", "source_file": "AuraFitness/Models/SeedData.swift", "source_location": "L31", "_callable": true}, {"id": "c_users_muska_onedrive_documents_app_development_aura_fitness_tracker_aurafitness_models_seeddata_stableid_warmupstep", "label": ".warmupStep()", "file_type": "code", "source_file": "AuraFitness/Models/SeedData.swift", "source_location": "L38", "_callable": true}, {"id": "int", "label": "Int", "file_type": "code", "source_file": "", "source_location": "", "origin_file": "C:\\Users\\muska\\OneDrive\\Documents\\App Development\\Aura Fitness Tracker\\AuraFitness\\Models\\SeedData.swift"}, {"id": "c_users_muska_onedrive_documents_app_development_aura_fitness_tracker_aurafitness_models_seeddata_stableid_v5", "label": ".v5()", "file_type": "code", "source_file": "AuraFitness/Models/SeedData.swift", "source_location": "L45", "_callable": true}, {"id": "c_users_muska_onedrive_documents_app_development_aura_fitness_tracker_aurafitness_models_seeddata_exerciselibrary", "label": "ExerciseLibrary", "file_type": "code", "source_file": "AuraFitness/Models/SeedData.swift", "source_location": "L57", "_callable": true}, {"id": "exercise", "label": "Exercise", "file_type": "code", "source_file": "", "source_location": "", "origin_file": "C:\\Users\\muska\\OneDrive\\Documents\\App Development\\Aura Fitness Tracker\\AuraFitness\\Models\\SeedData.swift"}, {"id": "c_users_muska_onedrive_documents_app_development_aura_fitness_tracker_aurafitness_models_seeddata_exerciselibrary_ex", "label": ".ex()", "file_type": "code", "source_file": "AuraFitness/Models/SeedData.swift", "source_location": "L366", "_callable": true}, {"id": "bool", "label": "Bool", "file_type": "code", "source_file": "", "source_location": "", "origin_file": "C:\\Users\\muska\\OneDrive\\Documents\\App Development\\Aura Fitness Tracker\\AuraFitness\\Models\\SeedData.swift"}, {"id": "prrecord", "label": "PRRecord", "file_type": "code", "source_file": "", "source_location": "", "origin_file": "C:\\Users\\muska\\OneDrive\\Documents\\App Development\\Aura Fitness Tracker\\AuraFitness\\Models\\SeedData.swift"}, {"id": "targetrecord", "label": "TargetRecord", "file_type": "code", "source_file": "", "source_location": "", "origin_file": "C:\\Users\\muska\\OneDrive\\Documents\\App Development\\Aura Fitness Tracker\\AuraFitness\\Models\\SeedData.swift"}, {"id": "sethistory", "label": "SetHistory", "file_type": "code", "source_file": "", "source_location": "", "origin_file": "C:\\Users\\muska\\OneDrive\\Documents\\App Development\\Aura Fitness Tracker\\AuraFitness\\Models\\SeedData.swift"}, {"id": "warmupset", "label": "WarmupSet", "file_type": "code", "source_file": "", "source_location": "", "origin_file": "C:\\Users\\muska\\OneDrive\\Documents\\App Development\\Aura Fitness Tracker\\AuraFitness\\Models\\SeedData.swift"}, {"id": "c_users_muska_onedrive_documents_app_development_aura_fitness_tracker_aurafitness_models_seeddata_seeddata", "label": "SeedData", "file_type": "code", "source_file": "AuraFitness/Models/SeedData.swift", "source_location": "L401", "_callable": true}, {"id": "program", "label": "Program", "file_type": "code", "source_file": "", "source_location": "", "origin_file": "C:\\Users\\muska\\OneDrive\\Documents\\App Development\\Aura Fitness Tracker\\AuraFitness\\Models\\SeedData.swift"}, {"id": "c_users_muska_onedrive_documents_app_development_aura_fitness_tracker_aurafitness_models_seeddata_seeddata_emptyworkout", "label": ".emptyWorkout()", "file_type": "code", "source_file": "AuraFitness/Models/SeedData.swift", "source_location": "L408", "_callable": true}, {"id": "workout", "label": "Workout", "file_type": "code", "source_file": "", "source_location": "", "origin_file": "C:\\Users\\muska\\OneDrive\\Documents\\App Development\\Aura Fitness Tracker\\AuraFitness\\Models\\SeedData.swift"}], "edges": [{"source": "c_users_muska_onedrive_documents_app_development_aura_fitness_tracker_aurafitness_models_seeddata_swift", "target": "foundation", "relation": "imports", "context": "import", "confidence": "EXTRACTED", "source_file": "AuraFitness/Models/SeedData.swift", "source_location": "L1", "weight": 1.0}, {"source": "c_users_muska_onedrive_documents_app_development_aura_fitness_tracker_aurafitness_models_seeddata_swift", "target": "cryptokit", "relation": "imports", "context": "import", "confidence": "EXTRACTED", "source_file": "AuraFitness/Models/SeedData.swift", "source_location": "L2", "weight": 1.0}, {"source": "c_users_muska_onedrive_documents_app_development_aura_fitness_tracker_aurafitness_models_seeddata_swift", "target": "c_users_muska_onedrive_documents_app_development_aura_fitness_tracker_aurafitness_models_seeddata_stableid", "relation": "contains", "confidence": "EXTRACTED", "source_file": "AuraFitness/Models/SeedData.swift", "source_location": "L18", "weight": 1.0}, {"source": "c_users_muska_onedrive_documents_app_development_aura_fitness_tracker_aurafitness_models_seeddata_stableid", "target": "c_users_muska_onedrive_documents_app_development_aura_fitness_tracker_aurafitness_models_seeddata_stableid_program", "relation": "method", "confidence": "EXTRACTED", "source_file": "AuraFitness/Models/SeedData.swift", "source_location": "L23", "weight": 1.0}, {"source": "c_users_muska_onedrive_documents_app_development_aura_fitness_tracker_aurafitness_models_seeddata_stableid_program", "target": "string", "relation": "references", "confidence": "EXTRACTED", "source_file": "AuraFitness/Models/SeedData.swift", "source_location": "L23", "weight": 1.0, "context": "parameter_type"}, {"source": "c_users_muska_onedrive_documents_app_development_aura_fitness_tracker_aurafitness_models_seeddata_stableid_program", "target": "uuid", "relation": "references", "confidence": "EXTRACTED", "source_file": "AuraFitness/Models/SeedData.swift", "source_location": "L23", "weight": 1.0, "context": "return_type"}, {"source": "c_users_muska_onedrive_documents_app_development_aura_fitness_tracker_aurafitness_models_seeddata_stableid", "target": "c_users_muska_onedrive_documents_app_development_aura_fitness_tracker_aurafitness_models_seeddata_stableid_workout", "relation": "method", "confidence": "EXTRACTED", "source_file": "AuraFitness/Models/SeedData.swift", "source_location": "L24", "weight": 1.0}, {"source": "c_users_muska_onedrive_documents_app_development_aura_fitness_tracker_aurafitness_models_seeddata_stableid_workout", "target": "string", "relation": "references", "confidence": "EXTRACTED", "source_file": "AuraFitness/Models/SeedData.swift", "source_location": "L24", "weight": 1.0, "context": "parameter_type"}, {"source": "c_users_muska_onedrive_documents_app_development_aura_fitness_tracker_aurafitness_models_seeddata_stableid_workout", "target": "uuid", "relation": "references", "confidence": "EXTRACTED", "source_file": "AuraFitness/Models/SeedData.swift", "source_location": "L24", "weight": 1.0, "context": "return_type"}, {"source": "c_users_muska_onedrive_documents_app_development_aura_fitness_tracker_aurafitness_models_seeddata_stableid", "target": "c_users_muska_onedrive_documents_app_development_aura_fitness_tracker_aurafitness_models_seeddata_stableid_exercise", "relation": "method", "confidence": "EXTRACTED", "source_file": "AuraFitness/Models/SeedData.swift", "source_location": "L31", "weight": 1.0}, {"source": "c_users_muska_onedrive_documents_app_development_aura_fitness_tracker_aurafitness_models_seeddata_stableid_exercise", "target": "string", "relation": "references", "confidence": "EXTRACTED", "source_file": "AuraFitness/Models/SeedData.swift", "source_location": "L31", "weight": 1.0, "context": "parameter_type"}, {"source": "c_users_muska_onedrive_documents_app_development_aura_fitness_tracker_aurafitness_models_seeddata_stableid_exercise", "target": "uuid", "relation": "references", "confidence": "EXTRACTED", "source_file": "AuraFitness/Models/SeedData.swift", "source_location": "L31", "weight": 1.0, "context": "return_type"}, {"source": "c_users_muska_onedrive_documents_app_development_aura_fitness_tracker_aurafitness_models_seeddata_stableid", "target": "c_users_muska_onedrive_documents_app_development_aura_fitness_tracker_aurafitness_models_seeddata_stableid_warmupstep", "relation": "method", "confidence": "EXTRACTED", "source_file": "AuraFitness/Models/SeedData.swift", "source_location": "L38", "weight": 1.0}, {"source": "c_users_muska_onedrive_documents_app_development_aura_fitness_tracker_aurafitness_models_seeddata_stableid_warmupstep", "target": "string", "relation": "references", "confidence": "EXTRACTED", "source_file": "AuraFitness/Models/SeedData.swift", "source_location": "L38", "weight": 1.0, "context": "parameter_type"}, {"source": "c_users_muska_onedrive_documents_app_development_aura_fitness_tracker_aurafitness_models_seeddata_stableid_warmupstep", "target": "int", "relation": "references", "confidence": "EXTRACTED", "source_file": "AuraFitness/Models/SeedData.swift", "source_location": "L38", "weight": 1.0, "context": "parameter_type"}, {"source": "c_users_muska_onedrive_documents_app_development_aura_fitness_tracker_aurafitness_models_seeddata_stableid_warmupstep", "target": "uuid", "relation": "references", "confidence": "EXTRACTED", "source_file": "AuraFitness/Models/SeedData.swift", "source_location": "L38", "weight": 1.0, "context": "return_type"}, {"source": "c_users_muska_onedrive_documents_app_development_aura_fitness_tracker_aurafitness_models_seeddata_stableid", "target": "c_users_muska_onedrive_documents_app_development_aura_fitness_tracker_aurafitness_models_seeddata_stableid_v5", "relation": "method", "confidence": "EXTRACTED", "source_file": "AuraFitness/Models/SeedData.swift", "source_location": "L45", "weight": 1.0}, {"source": "c_users_muska_onedrive_documents_app_development_aura_fitness_tracker_aurafitness_models_seeddata_stableid_v5", "target": "string", "relation": "references", "confidence": "EXTRACTED", "source_file": "AuraFitness/Models/SeedData.swift", "source_location": "L45", "weight": 1.0, "context": "parameter_type"}, {"source": "c_users_muska_onedrive_documents_app_development_aura_fitness_tracker_aurafitness_models_seeddata_stableid_v5", "target": "uuid", "relation": "references", "confidence": "EXTRACTED", "source_file": "AuraFitness/Models/SeedData.swift", "source_location": "L45", "weight": 1.0, "context": "return_type"}, {"source": "c_users_muska_onedrive_documents_app_development_aura_fitness_tracker_aurafitness_models_seeddata_swift", "target": "c_users_muska_onedrive_documents_app_development_aura_fitness_tracker_aurafitness_models_seeddata_exerciselibrary", "relation": "contains", "confidence": "EXTRACTED", "source_file": "AuraFitness/Models/SeedData.swift", "source_location": "L57", "weight": 1.0}, {"source": "c_users_muska_onedrive_documents_app_development_aura_fitness_tracker_aurafitness_models_seeddata_exerciselibrary", "target": "exercise", "relation": "references", "confidence": "EXTRACTED", "source_file": "AuraFitness/Models/SeedData.swift", "source_location": "L58", "weight": 1.0, "context": "field"}, {"source": "c_users_muska_onedrive_documents_app_development_aura_fitness_tracker_aurafitness_models_seeddata_exerciselibrary", "target": "exercise", "relation": "references", "confidence": "EXTRACTED", "source_file": "AuraFitness/Models/SeedData.swift", "source_location": "L61", "weight": 1.0, "context": "field"}, {"source": "c_users_muska_onedrive_documents_app_development_aura_fitness_tracker_aurafitness_models_seeddata_exerciselibrary", "target": "exercise", "relation": "references", "confidence": "EXTRACTED", "source_file": "AuraFitness/Models/SeedData.swift", "source_location": "L96", "weight": 1.0, "context": "field"}, {"source": "c_users_muska_onedrive_documents_app_development_aura_fitness_tracker_aurafitness_models_seeddata_exerciselibrary", "target": "exercise", "relation": "references", "confidence": "EXTRACTED", "source_file": "AuraFitness/Models/SeedData.swift", "source_location": "L131", "weight": 1.0, "context": "field"}, {"source": "c_users_muska_onedrive_documents_app_development_aura_fitness_tracker_aurafitness_models_seeddata_exerciselibrary", "target": "exercise", "relation": "references", "confidence": "EXTRACTED", "source_file": "AuraFitness/Models/SeedData.swift", "source_location": "L164", "weight": 1.0, "context": "field"}, {"source": "c_users_muska_onedrive_documents_app_development_aura_fitness_tracker_aurafitness_models_seeddata_exerciselibrary", "target": "exercise", "relation": "references", "confidence": "EXTRACTED", "source_file": "AuraFitness/Models/SeedData.swift", "source_location": "L200", "weight": 1.0, "context": "field"}, {"source": "c_users_muska_onedrive_documents_app_development_aura_fitness_tracker_aurafitness_models_seeddata_exerciselibrary", "target": "exercise", "relation": "references", "confidence": "EXTRACTED", "source_file": "AuraFitness/Models/SeedData.swift", "source_location": "L240", "weight": 1.0, "context": "field"}, {"source": "c_users_muska_onedrive_documents_app_development_aura_fitness_tracker_aurafitness_models_seeddata_exerciselibrary", "target": "exercise", "relation": "references", "confidence": "EXTRACTED", "source_file": "AuraFitness/Models/SeedData.swift", "source_location": "L262", "weight": 1.0, "context": "field"}, {"source": "c_users_muska_onedrive_documents_app_development_aura_fitness_tracker_aurafitness_models_seeddata_exerciselibrary", "target": "exercise", "relation": "references", "confidence": "EXTRACTED", "source_file": "AuraFitness/Models/SeedData.swift", "source_location": "L293", "weight": 1.0, "context": "field"}, {"source": "c_users_muska_onedrive_documents_app_development_aura_fitness_tracker_aurafitness_models_seeddata_exerciselibrary", "target": "c_users_muska_onedrive_documents_app_development_aura_fitness_tracker_aurafitness_models_seeddata_exerciselibrary_ex", "relation": "method", "confidence": "EXTRACTED", "source_file": "AuraFitness/Models/SeedData.swift", "source_location": "L366", "weight": 1.0}, {"source": "c_users_muska_onedrive_documents_app_development_aura_fitness_tracker_aurafitness_models_seeddata_exerciselibrary_ex", "target": "string", "relation": "references", "confidence": "EXTRACTED", "source_file": "AuraFitness/Models/SeedData.swift", "source_location": "L366", "weight": 1.0, "context": "parameter_type"}, {"source": "c_users_muska_onedrive_documents_app_development_aura_fitness_tracker_aurafitness_models_seeddata_exerciselibrary_ex", "target": "string", "relation": "references", "confidence": "EXTRACTED", "source_file": "AuraFitness/Models/SeedData.swift", "source_location": "L366", "weight": 1.0, "context": "parameter_type"}, {"source": "c_users_muska_onedrive_documents_app_development_aura_fitness_tracker_aurafitness_models_seeddata_exerciselibrary_ex", "target": "string", "relation": "references", "confidence": "EXTRACTED", "source_file": "AuraFitness/Models/SeedData.swift", "source_location": "L366", "weight": 1.0, "context": "parameter_type"}, {"source": "c_users_muska_onedrive_documents_app_development_aura_fitness_tracker_aurafitness_models_seeddata_exerciselibrary_ex", "target": "string", "relation": "references", "confidence": "EXTRACTED", "source_file": "AuraFitness/Models/SeedData.swift", "source_location": "L366", "weight": 1.0, "context": "parameter_type"}, {"source": "c_users_muska_onedrive_documents_app_development_aura_fitness_tracker_aurafitness_models_seeddata_exerciselibrary_ex", "target": "string", "relation": "references", "confidence": "EXTRACTED", "source_file": "AuraFitness/Models/SeedData.swift", "source_location": "L366", "weight": 1.0, "context": "parameter_type"}, {"source": "c_users_muska_onedrive_documents_app_development_aura_fitness_tracker_aurafitness_models_seeddata_exerciselibrary_ex", "target": "bool", "relation": "references", "confidence": "EXTRACTED", "source_file": "AuraFitness/Models/SeedData.swift", "source_location": "L366", "weight": 1.0, "context": "parameter_type"}, {"source": "c_users_muska_onedrive_documents_app_development_aura_fitness_tracker_aurafitness_models_seeddata_exerciselibrary_ex", "target": "string", "relation": "references", "confidence": "EXTRACTED", "source_file": "AuraFitness/Models/SeedData.swift", "source_location": "L366", "weight": 1.0, "context": "parameter_type"}, {"source": "c_users_muska_onedrive_documents_app_development_aura_fitness_tracker_aurafitness_models_seeddata_exerciselibrary_ex", "target": "string", "relation": "references", "confidence": "EXTRACTED", "source_file": "AuraFitness/Models/SeedData.swift", "source_location": "L366", "weight": 1.0, "context": "parameter_type"}, {"source": "c_users_muska_onedrive_documents_app_development_aura_fitness_tracker_aurafitness_models_seeddata_exerciselibrary_ex", "target": "int", "relation": "references", "confidence": "EXTRACTED", "source_file": "AuraFitness/Models/SeedData.swift", "source_location": "L366", "weight": 1.0, "context": "parameter_type"}, {"source": "c_users_muska_onedrive_documents_app_development_aura_fitness_tracker_aurafitness_models_seeddata_exerciselibrary_ex", "target": "int", "relation": "references", "confidence": "EXTRACTED", "source_file": "AuraFitness/Models/SeedData.swift", "source_location": "L366", "weight": 1.0, "context": "parameter_type"}, {"source": "c_users_muska_onedrive_documents_app_development_aura_fitness_tracker_aurafitness_models_seeddata_exerciselibrary_ex", "target": "prrecord", "relation": "references", "confidence": "EXTRACTED", "source_file": "AuraFitness/Models/SeedData.swift", "source_location": "L366", "weight": 1.0, "context": "parameter_type"}, {"source": "c_users_muska_onedrive_documents_app_development_aura_fitness_tracker_aurafitness_models_seeddata_exerciselibrary_ex", "target": "targetrecord", "relation": "references", "confidence": "EXTRACTED", "source_file": "AuraFitness/Models/SeedData.swift", "source_location": "L366", "weight": 1.0, "context": "parameter_type"}, {"source": "c_users_muska_onedrive_documents_app_development_aura_fitness_tracker_aurafitness_models_seeddata_exerciselibrary_ex", "target": "sethistory", "relation": "references", "confidence": "EXTRACTED", "source_file": "AuraFitness/Models/SeedData.swift", "source_location": "L366", "weight": 1.0, "context": "parameter_type"}, {"source": "c_users_muska_onedrive_documents_app_development_aura_fitness_tracker_aurafitness_models_seeddata_exerciselibrary_ex", "target": "warmupset", "relation": "references", "confidence": "EXTRACTED", "source_file": "AuraFitness/Models/SeedData.swift", "source_location": "L366", "weight": 1.0, "context": "parameter_type"}, {"source": "c_users_muska_onedrive_documents_app_development_aura_fitness_tracker_aurafitness_models_seeddata_exerciselibrary_ex", "target": "string", "relation": "references", "confidence": "EXTRACTED", "source_file": "AuraFitness/Models/SeedData.swift", "source_location": "L366", "weight": 1.0, "context": "parameter_type"}, {"source": "c_users_muska_onedrive_documents_app_development_aura_fitness_tracker_aurafitness_models_seeddata_exerciselibrary_ex", "target": "exercise", "relation": "references", "confidence": "EXTRACTED", "source_file": "AuraFitness/Models/SeedData.swift", "source_location": "L366", "weight": 1.0, "context": "return_type"}, {"source": "c_users_muska_onedrive_documents_app_development_aura_fitness_tracker_aurafitness_models_seeddata_swift", "target": "c_users_muska_onedrive_documents_app_development_aura_fitness_tracker_aurafitness_models_seeddata_seeddata", "relation": "contains", "confidence": "EXTRACTED", "source_file": "AuraFitness/Models/SeedData.swift", "source_location": "L401", "weight": 1.0}, {"source": "c_users_muska_onedrive_documents_app_development_aura_fitness_tracker_aurafitness_models_seeddata_seeddata", "target": "program", "relation": "references", "confidence": "EXTRACTED", "source_file": "AuraFitness/Models/SeedData.swift", "source_location": "L405", "weight": 1.0, "context": "field"}, {"source": "c_users_muska_onedrive_documents_app_development_aura_fitness_tracker_aurafitness_models_seeddata_seeddata", "target": "c_users_muska_onedrive_documents_app_development_aura_fitness_tracker_aurafitness_models_seeddata_seeddata_emptyworkout", "relation": "method", "confidence": "EXTRACTED", "source_file": "AuraFitness/Models/SeedData.swift", "source_location": "L408", "weight": 1.0}, {"source": "c_users_muska_onedrive_documents_app_development_aura_fitness_tracker_aurafitness_models_seeddata_seeddata_emptyworkout", "target": "workout", "relation": "references", "confidence": "EXTRACTED", "source_file": "AuraFitness/Models/SeedData.swift", "source_location": "L408", "weight": 1.0, "context": "return_type"}, {"source": "c_users_muska_onedrive_documents_app_development_aura_fitness_tracker_aurafitness_models_seeddata_stableid_program", "target": "c_users_muska_onedrive_documents_app_development_aura_fitness_tracker_aurafitness_models_seeddata_stableid_v5", "relation": "calls", "context": "call", "confidence": "EXTRACTED", "source_file": "AuraFitness/Models/SeedData.swift", "source_location": "L23", "weight": 1.0}, {"source": "c_users_muska_onedrive_documents_app_development_aura_fitness_tracker_aurafitness_models_seeddata_stableid_workout", "target": "c_users_muska_onedrive_documents_app_development_aura_fitness_tracker_aurafitness_models_seeddata_stableid_v5", "relation": "calls", "context": "call", "confidence": "EXTRACTED", "source_file": "AuraFitness/Models/SeedData.swift", "source_location": "L24", "weight": 1.0}, {"source": "c_users_muska_onedrive_documents_app_development_aura_fitness_tracker_aurafitness_models_seeddata_stableid_exercise", "target": "c_users_muska_onedrive_documents_app_development_aura_fitness_tracker_aurafitness_models_seeddata_stableid_v5", "relation": "calls", "context": "call", "confidence": "EXTRACTED", "source_file": "AuraFitness/Models/SeedData.swift", "source_location": "L31", "weight": 1.0}, {"source": "c_users_muska_onedrive_documents_app_development_aura_fitness_tracker_aurafitness_models_seeddata_stableid_warmupstep", "target": "c_users_muska_onedrive_documents_app_development_aura_fitness_tracker_aurafitness_models_seeddata_stableid_v5", "relation": "calls", "context": "call", "confidence": "EXTRACTED", "source_file": "AuraFitness/Models/SeedData.swift", "source_location": "L39", "weight": 1.0}, {"source": "c_users_muska_onedrive_documents_app_development_aura_fitness_tracker_aurafitness_models_seeddata_stableid_v5", "target": "uuid", "relation": "calls", "context": "call", "confidence": "EXTRACTED", "source_file": "AuraFitness/Models/SeedData.swift", "source_location": "L51", "weight": 1.0}, {"source": "c_users_muska_onedrive_documents_app_development_aura_fitness_tracker_aurafitness_models_seeddata_exerciselibrary_ex", "target": "exercise", "relation": "calls", "context": "call", "confidence": "EXTRACTED", "source_file": "AuraFitness/Models/SeedData.swift", "source_location": "L374", "weight": 1.0}, {"source": "c_users_muska_onedrive_documents_app_development_aura_fitness_tracker_aurafitness_models_seeddata_seeddata_emptyworkout", "target": "workout", "relation": "calls", "context": "call", "confidence": "EXTRACTED", "source_file": "AuraFitness/Models/SeedData.swift", "source_location": "L409", "weight": 1.0}], "raw_calls": [{"caller_nid": "c_users_muska_onedrive_documents_app_development_aura_fitness_tracker_aurafitness_models_seeddata_stableid_v5", "callee": "withUnsafeBytes", "is_member_call": false, "source_file": "AuraFitness/Models/SeedData.swift", "source_location": "L46", "receiver": null}, {"caller_nid": "c_users_muska_onedrive_documents_app_development_aura_fitness_tracker_aurafitness_models_seeddata_stableid_v5", "callee": "append", "is_member_call": true, "source_file": "AuraFitness/Models/SeedData.swift", "source_location": "L47", "receiver": "input"}, {"caller_nid": "c_users_muska_onedrive_documents_app_development_aura_fitness_tracker_aurafitness_models_seeddata_stableid_v5", "callee": "prefix", "is_member_call": true, "source_file": "AuraFitness/Models/SeedData.swift", "source_location": "L48", "receiver": null}, {"caller_nid": "c_users_muska_onedrive_documents_app_development_aura_fitness_tracker_aurafitness_models_seeddata_stableid_v5", "callee": "Data", "is_member_call": false, "source_file": "AuraFitness/Models/SeedData.swift", "source_location": "L48", "receiver": null}, {"caller_nid": "c_users_muska_onedrive_documents_app_development_aura_fitness_tracker_aurafitness_models_seeddata_stableid_v5", "callee": "b", "is_member_call": false, "source_file": "AuraFitness/Models/SeedData.swift", "source_location": "L49", "receiver": null}, {"caller_nid": "c_users_muska_onedrive_documents_app_development_aura_fitness_tracker_aurafitness_models_seeddata_stableid_v5", "callee": "b", "is_member_call": false, "source_file": "AuraFitness/Models/SeedData.swift", "source_location": "L49", "receiver": null}, {"caller_nid": "c_users_muska_onedrive_documents_app_development_aura_fitness_tracker_aurafitness_models_seeddata_stableid_v5", "callee": "b", "is_member_call": false, "source_file": "AuraFitness/Models/SeedData.swift", "source_location": "L50", "receiver": null}, {"caller_nid": "c_users_muska_onedrive_documents_app_development_aura_fitness_tracker_aurafitness_models_seeddata_stableid_v5", "callee": "b", "is_member_call": false, "source_file": "AuraFitness/Models/SeedData.swift", "source_location": "L50", "receiver": null}, {"caller_nid": "c_users_muska_onedrive_documents_app_development_aura_fitness_tracker_aurafitness_models_seeddata_stableid_v5", "callee": "b", "is_member_call": false, "source_file": "AuraFitness/Models/SeedData.swift", "source_location": "L51", "receiver": null}, {"caller_nid": "c_users_muska_onedrive_documents_app_development_aura_fitness_tracker_aurafitness_models_seeddata_stableid_v5", "callee": "b", "is_member_call": false, "source_file": "AuraFitness/Models/SeedData.swift", "source_location": "L51", "receiver": null}, {"caller_nid": "c_users_muska_onedrive_documents_app_development_aura_fitness_tracker_aurafitness_models_seeddata_stableid_v5", "callee": "b", "is_member_call": false, "source_file": "AuraFitness/Models/SeedData.swift", "source_location": "L51", "receiver": null}, {"caller_nid": "c_users_muska_onedrive_documents_app_development_aura_fitness_tracker_aurafitness_models_seeddata_stableid_v5", "callee": "b", "is_member_call": false, "source_file": "AuraFitness/Models/SeedData.swift", "source_location": "L51", "receiver": null}, {"caller_nid": "c_users_muska_onedrive_documents_app_development_aura_fitness_tracker_aurafitness_models_seeddata_stableid_v5", "callee": "b", "is_member_call": false, "source_file": "AuraFitness/Models/SeedData.swift", "source_location": "L51", "receiver": null}, {"caller_nid": "c_users_muska_onedrive_documents_app_development_aura_fitness_tracker_aurafitness_models_seeddata_stableid_v5", "callee": "b", "is_member_call": false, "source_file": "AuraFitness/Models/SeedData.swift", "source_location": "L51", "receiver": null}, {"caller_nid": "c_users_muska_onedrive_documents_app_development_aura_fitness_tracker_aurafitness_models_seeddata_stableid_v5", "callee": "b", "is_member_call": false, "source_file": "AuraFitness/Models/SeedData.swift", "source_location": "L51", "receiver": null}, {"caller_nid": "c_users_muska_onedrive_documents_app_development_aura_fitness_tracker_aurafitness_models_seeddata_stableid_v5", "callee": "b", "is_member_call": false, "source_file": "AuraFitness/Models/SeedData.swift", "source_location": "L51", "receiver": null}, {"caller_nid": "c_users_muska_onedrive_documents_app_development_aura_fitness_tracker_aurafitness_models_seeddata_stableid_v5", "callee": "b", "is_member_call": false, "source_file": "AuraFitness/Models/SeedData.swift", "source_location": "L52", "receiver": null}, {"caller_nid": "c_users_muska_onedrive_documents_app_development_aura_fitness_tracker_aurafitness_models_seeddata_stableid_v5", "callee": "b", "is_member_call": false, "source_file": "AuraFitness/Models/SeedData.swift", "source_location": "L52", "receiver": null}, {"caller_nid": "c_users_muska_onedrive_documents_app_development_aura_fitness_tracker_aurafitness_models_seeddata_stableid_v5", "callee": "b", "is_member_call": false, "source_file": "AuraFitness/Models/SeedData.swift", "source_location": "L52", "receiver": null}, {"caller_nid": "c_users_muska_onedrive_documents_app_development_aura_fitness_tracker_aurafitness_models_seeddata_stableid_v5", "callee": "b", "is_member_call": false, "source_file": "AuraFitness/Models/SeedData.swift", "source_location": "L52", "receiver": null}, {"caller_nid": "c_users_muska_onedrive_documents_app_development_aura_fitness_tracker_aurafitness_models_seeddata_stableid_v5", "callee": "b", "is_member_call": false, "source_file": "AuraFitness/Models/SeedData.swift", "source_location": "L52", "receiver": null}, {"caller_nid": "c_users_muska_onedrive_documents_app_development_aura_fitness_tracker_aurafitness_models_seeddata_stableid_v5", "callee": "b", "is_member_call": false, "source_file": "AuraFitness/Models/SeedData.swift", "source_location": "L52", "receiver": null}, {"caller_nid": "c_users_muska_onedrive_documents_app_development_aura_fitness_tracker_aurafitness_models_seeddata_stableid_v5", "callee": "b", "is_member_call": false, "source_file": "AuraFitness/Models/SeedData.swift", "source_location": "L52", "receiver": null}, {"caller_nid": "c_users_muska_onedrive_documents_app_development_aura_fitness_tracker_aurafitness_models_seeddata_stableid_v5", "callee": "b", "is_member_call": false, "source_file": "AuraFitness/Models/SeedData.swift", "source_location": "L52", "receiver": null}, {"caller_nid": "c_users_muska_onedrive_documents_app_development_aura_fitness_tracker_aurafitness_models_seeddata_exerciselibrary_ex", "callee": "WorkoutSet", "is_member_call": false, "source_file": "AuraFitness/Models/SeedData.swift", "source_location": "L380", "receiver": null}], "swift_type_table": {"path": "C:\\Users\\muska\\OneDrive\\Documents\\App Development\\Aura Fitness Tracker\\AuraFitness\\Models\\SeedData.swift", "table": {"name": "String", "exercise": "String", "index": "Int", "all": "Exercise", "chest": "Exercise", "back": "Exercise", "shoulders": "Exercise", "arms": "Exercise", "legs": "Exercise", "core": "Exercise", "cardio": "Exercise", "smith": "Exercise", "muscle": "String", "groups": "String", "equip": "String", "diff": "String", "isCable": "Bool", "pulley": "String", "repRange": "String", "planned": "Int", "sets": "Int", "pr": "PRRecord", "target": "TargetRecord", "history": "SetHistory", "warmup": "WarmupSet", "hint": "String", "programs": "Program", "b": "Array", "e": "Exercise"}}}